macromol_gym/__init__.py
macromol_gym/cath.py
macromol_gym/database_io.py
macromol_gym/density.py
macromol_gym/geometry.py
macromol_gym/init.py
macromol_gym/interpro.py
macromol_gym/pick.py
macromol_gym/pymol.py
macromol_gym/split.py
macromol_gym-1.1.0.dist-info/entry_points.txt
macromol_gym-1.1.0.dist-info/WHEEL
macromol_gym-1.1.0.dist-info/METADATA
macromol_gym-1.1.0.dist-info/RECORD
