Metadata-Version: 2.3
Name: macromol_gym
Version: 1.1.0
Summary: Macromolecular training sets that emphasize protein/non-protein interactions.
Author-email: Kale Kundert <kale@thekunderts.net>
Requires-Python: ~=3.10
Classifier: Programming Language :: Python :: 3
Requires-Dist: aiohttp
Requires-Dist: docopt
Requires-Dist: icosphere
Requires-Dist: macromol_census
Requires-Dist: macromol_dataframe
Requires-Dist: macromol_voxelize
Requires-Dist: more_itertools
Requires-Dist: nestedtext
Requires-Dist: networkx
Requires-Dist: numpy
Requires-Dist: periodictable
Requires-Dist: pipeline_func
Requires-Dist: reprfunc
Requires-Dist: scikit-learn
Requires-Dist: scipy
Requires-Dist: tqdm
Requires-Dist: xxhash
Requires-Dist: pytest ; extra == "test"
Requires-Dist: parametrize_from_file ; extra == "test"
Requires-Dist: pytest_unordered ; extra == "test"
Requires-Dist: pytest_tmp_files ; extra == "test"
Project-URL: Bug Tracker, https://github.com/kalekundert/macromol_gym/issues
Project-URL: Continuous Integration, https://github.com/kalekundert/macromol_gym/actions
Project-URL: Documentation, https://macromol-gym.readthedocs.io/en/latest/
Project-URL: Test Coverage, https://coveralls.io/github/kalekundert/macromol_gym
Project-URL: Version Control, https://github.com/kalekundert/macromol_gym
Provides-Extra: test
